bridgebots/__init__.py
bridgebots/bids.py
bridgebots/board_record.py
bridgebots/convert_scratch.py
bridgebots/deal.py
bridgebots/deal_enums.py
bridgebots/deal_utils.py
bridgebots/double_dummy.py
bridgebots/lin.py
bridgebots/pbn.py
bridgebots/play_utils.py
bridgebots/schemas.py
bridgebots-0.0.12.dist-info/WHEEL
bridgebots-0.0.12.dist-info/METADATA
bridgebots-0.0.12.dist-info/RECORD
