Metadata-Version: 2.1
Name: bridgebots
Version: 0.0.12
Summary: Data processing for Contract Bridge
License: MIT
Author: Forrest Rice
Author-email: forrest.d.rice@gmail.com
Requires-Python: >=3.7,<4.0
Classifier: License :: OSI Approved :: MIT License
Classifier: Programming Language :: Python :: 3
Classifier: Programming Language :: Python :: 3.7
Classifier: Programming Language :: Python :: 3.8
Classifier: Programming Language :: Python :: 3.9
Classifier: Programming Language :: Python :: 3.10
Classifier: Programming Language :: Python :: 3.11
Requires-Dist: marshmallow (>=3.19.0,<4.0.0)
